LICENSE
MANIFEST.in
README.md
setup.py
drive_sync.egg-info/PKG-INFO
drive_sync.egg-info/SOURCES.txt
drive_sync.egg-info/dependency_links.txt
drive_sync.egg-info/entry_points.txt
drive_sync.egg-info/not-zip-safe
drive_sync.egg-info/requires.txt
drive_sync.egg-info/top_level.txt
gdrive_sync/.client_secrets.json
gdrive_sync/__init__.py
gdrive_sync/auth.py
gdrive_sync/cron_handle.py
gdrive_sync/edit_config.py
gdrive_sync/file_add.py
gdrive_sync/file_ops.py
gdrive_sync/main.py
gdrive_sync/config_dicts/config.json
gdrive_sync/config_dicts/formats.json
gdrive_sync/config_dicts/mime_dict.json
gdrive_sync/docs/args.txt
gdrive_sync/docs/readme.txt
gdrive_sync/docs/ver_info.txt