Metadata-Version: 1.1
Name: drive-sync
Version: 1.222
Summary: GDrive_Sync is an automatic folder syncing client for Google Drive
Home-page: http://github.com/thealphadollar/GDrive_Sync
Author: thealphadollar
Author-email: shivam.cs.iit.kgp@gmail.com
License: MIT
Keywords: google-drive GDrive automatic sync GDrive manager
Platform: UNKNOWN
Classifier: Development Status :: 4 - Beta
Classifier: License :: OSI Approved :: MIT License
Classifier: Programming Language :: Python :: 2
Classifier: Programming Language :: Python :: 3
Classifier: Intended Audience :: End Users/Desktop
Classifier: Operating System :: POSIX :: Linux
Classifier: Topic :: Utilities
